{
  "slug": "match-preview-ausw-vs-wiw-2026-06-30",
  "title": "Australia Women vs West Indies Women Preview — Pitch, Weather & Lineup | 1st Semi-Final",
  "description": "Australia Women vs West Indies Women preview with pitch report, weather forecast, probable lineups, and betting insights for T20 on Tue, 30 Jun, 2026, 7:00 pm.",
  "excerpt": "Australia Women vs West Indies Women — pitch: Seam-friendly English conditions; overcast skies assist swing bowlers.… Weather: Light drizzle · High 23°C / Low 17°C · Rain: 0.6 mm · Wind: up to 15 km/h. Light…",
  "keywords": [
    "cricket news",
    "cricket match preview",
    "pitch report",
    "weather report",
    "cricket lineup",
    "live cricket betting",
    "reddy anna cricket",
    "Australia Women vs West Indies Women",
    "pitch report",
    "weather forecast"
  ],
  "category": "Cricket News",
  "publishedAt": "2026-06-30",
  "updatedAt": "2026-06-30",
  "readingTime": 7,
  "source": "Cricbuzz",
  "image": "/images/blog/cricket-hero.jpg",
  "imageAlt": "Australia Women vs West Indies Women cricket match preview — pitch and weather report",
  "blocks": [
    {
      "type": "p",
      "text": "Match preview: Australia Women face West Indies Women in 1st Semi-Final (T20) on Tue, 30 Jun, 2026, 7:00 pm at Kennington Oval London. Full pitch report, weather forecast, and squad details below."
    },
    {
      "type": "h2",
      "text": "Match Details",
      "id": "match-details"
    },
    {
      "type": "table",
      "headers": [
        "Detail",
        "Info"
      ],
      "rows": [
        [
          "Teams",
          "Australia Women vs West Indies Women"
        ],
        [
          "Format",
          "T20"
        ],
        [
          "Series",
          "ICC Women's T20 World Cup 2026"
        ],
        [
          "Date & Time (IST)",
          "Tue, 30 Jun, 2026, 7:00 pm"
        ],
        [
          "Venue",
          "Kennington Oval London"
        ],
        [
          "Status",
          "Match starts at Jun 30, 13:30 GMT"
        ]
      ]
    },
    {
      "type": "h2",
      "text": "Pitch Report",
      "id": "pitch-report"
    },
    {
      "type": "p",
      "text": "Seam-friendly English conditions; overcast skies assist swing bowlers."
    },
    {
      "type": "p",
      "text": "Expected par score: 250–300 (ODI)."
    },
    {
      "type": "h2",
      "text": "Weather Report",
      "id": "weather-report"
    },
    {
      "type": "p",
      "text": "Light drizzle · High 23°C / Low 17°C · Rain: 0.6 mm · Wind: up to 15 km/h. Light rain possible — overcast conditions could assist swing bowling early."
    },
    {
      "type": "h2",
      "text": "Team Lineups & Squads",
      "id": "lineups"
    },
    {
      "type": "p",
      "text": "International playing XI is announced at the toss. Check back on match day for confirmed line-ups."
    },
    {
      "type": "h2",
      "text": "Bet on Cricket with Reddy Anna Book",
      "id": "bet-with-reddy-anna"
    },
    {
      "type": "p",
      "text": "Use pitch reports, weather updates, and team news to make smarter cricket bets on Reddy Anna Book. Live odds on IPL, ODIs, Tests, and T20 leagues. New users get ₹5,000 welcome bonus."
    },
    {
      "type": "cta",
      "text": "Get your Reddy Anna Cricket ID on WhatsApp and bet on live cricket with instant deposits."
    }
  ]
}